Workbook

Sheet README — Intern Must Read First
A1: AIVI CAREER & CAMPUS OS — INTERN TESTING ASSIGNMENT & SAFETY PROTOCOL
A3: 1. What This File Is
A4: This workbook is your complete, authoritative testing assignment for AIVI Career Intelligence OS (B2C SaaS) and Multi-Tenant Campus OS (B2B).
A5: You are testing the end-to-end product user experience, functional workflows, error states, and security guards.
A6: CRITICAL PROTOCOL: All testing runs directly on the Production environment (https://aivilabs.com, Firebase project 'aivi-career').
A8: 2. Golden Safety Rules (Breaking ANY rule results in immediate removal from testing)
A9: ① Everything you test is the LIVE product — never reset, never delete, never seed, never pay unless the founder is literally sitting next to you running it.
A10: ② NEVER click 'Seed Demo Campus' or 'Reset Demo Campus' without Founder present — seeder reset and data purging are strictly founder-only.
A11: ③ Use ONLY the official test accounts provided on the 'Test Accounts & Setup' sheet (demo-sunrise campus accounts and founder-approved throwaway B2C account). Do not create other accounts, and do not touch any real user data you encounter.
A12: ④ Production uses LIVE Razorpay keys — test card details (e.g. 4111 1111 1111 1111) are NOT supported in live mode. Payment tests are strictly FOUNDER-ONLY live verification (real ₹399 Starter purchase + Razorpay dashboard refund). Interns must NEVER execute live payment transactions.
A13: ⑤ Never share credentials, API keys, production URLs, or tracker documents outside the engineering team.
A15: 3. Your Daily Workflow (7 Steps)
... A47: Real-Life Example: Login displays 'Invalid email or password' → Checks done: 1) Is email verified in Firebase Console? 2) confirm the URL bar shows https://aivilabs.com (production)? 3) Is password correct (caps lock off)? 4) Try password reset — if reset email arrives, account exists and password was entered wrong! (Marked Not a Bug).

Sheet Test Accounts & Setup
A1: AIVI CAREER & CAMPUS OS — SEEDED ACCOUNTS & ENVIRONMENT SETUP
A3: 1. Seeded Test Accounts Inventory (From Chapter 11)
A4: System Role | B4: Display Name | C4: Email Address | D4: Default Password | E4: Custom Claims / Scope | F4: Recommended Test Usage
A5: Platform Admin | B5: Platform Administrator | C5: abhi.triloki@gmail.com | D5: (User Configured) | E5: { role: 'platform_admin' } | F5: Suite S04 Platform Admin Console, tenant provisioning, demo seeder execution
A6: Tenant Admin (TPO) | B6: Dr. Alok Verma | C6: tpo.director@demo.aivilabs.com | D6: DemoUser@2026 | E6: { tenantId: 'demo-sunrise', role: 'tenant_admin' } | F6: Suite S05 TPO Dashboard, placement drives, CSV student import, staff management, billing
A7: Department Coordinator | B7: Prof. Sunita Rao | C7: coordinator.cse@demo.aivilabs.com | D7: DemoUser@2026 | E7: { tenantId: 'demo-sunrise', role: 'coordinator', branchScope: ['CSE'] } | F7: Suite S06 Coordinator branch scoping & CSE student roster management
A8: Student 1 (CSE Batch 26) | B8: Aarav Sharma | C8: student1@demo.aivilabs.com | D8: DemoStudent@2026 | E8: { tenantId: 'demo-sunrise', role: 'student' } | F8: Suite S07 Student drives, resume vault upload, vernacular mock interview (text & voice)
A9: Student 2 (ECE Batch 26) | B9: Aditi Verma | C9: student97@demo.aivilabs.com | D9: DemoStudent@2026 | E9: { tenantId: 'demo-sunrise', role: 'student' } | F9: Suite S07 ECE branch cross-department drive applications
A10: Student 3 (ME Batch 26) | B10: Ananya Gupta | C10: student169@demo.aivilabs.com | D10: DemoStudent@2026 | E10: { tenantId: 'demo-sunrise', role: 'student' } | F10: Suite S07 Mechanical engineering branch student testing
A12: 2. Production Environment Details & Gateway Protocol
A13: Environment Property | B13: Production Environment Configuration | C13: QA Safety & Testing Guidelines
A14: Firebase Project ID | B14: aivi-career | C14: Primary production Firebase infrastructure project.
A15: Canonical Web URL | B15: https://aivilabs.com (or https://aivi-career.web.app) | C15: All testing MUST confirm the URL bar shows https://aivilabs.com (production).
A16: Razorpay Key Mode | B16: LIVE Keys (rzp_live_...) | C16: LIVE Mode — Test cards (e.g. 4111 1111 1111 1111) are NOT supported on production.
A17: Payment Test Rule | B17: FOUNDER-ONLY Live Verification | C17: Payment tests are strictly FOUNDER-ONLY using real ₹399 transaction + Razorpay dashboard refund. Interns must NEVER execute transactions.
A18: Permitted Test Accounts | B18: demo-sunrise Campus & Throwaway B2C | C18: You test ONLY with demo-sunrise campus accounts and founder-approved throwaway B2C account. Do not touch real user data.
A19: Destructive Actions | B19: STRICTLY PROHIBITED FOR INTERNS | C19: Seeder reset ('resetDemoCampus'), tenant purging, and account deletions are strictly FOUNDER-ONLY with Founder present.
A20: 3. Intern Pre-Testing Setup Checklist
A21: 1. Launch Google Chrome browser (latest version).
A22: 2. Enable pop-ups for 'aivilabs.com' in Chrome Settings -> Privacy and Security -> Site Settings -> Pop-ups.
A23: 3. Enable microphone permissions for 'aivilabs.com' (required for Vernacular Voice Interviews).
A24: 4. Bookmark the Production URL (https://aivilabs.com) and keep the shared Google Drive evidence folder open in a separate tab.
A25: 5. Confirm the URL bar shows https://aivilabs.com (production) before executing any test case.
A27: 4. Sample Inputs for Testing (CSV Import & Negative Test Data)
A28: CSV Import Template Header: Full Name,Email,Enrollment No,Branch,CGPA,Graduation Year
A29: Row Type | B29: Full Name | C29: Email | D29: Enrollment No | E29: Branch | F29: CGPA | G29: Graduation Year / Notes
A30: Valid Row 1 | B30: Rohan Gupta | C30: rohan.gupta@demo.aivilabs.com | D30: SEC26CSE241 | E30: CSE | F30: 8.2 | G30: 2026
A31: Valid Row 2 | B31: Sneha Patel | C31: sneha.patel@demo.aivilabs.com | D31: SEC26ECE242 | E31: ECE | F31: 7.5 | G31: 2026
A32: Valid Row 3 | B32: Vipul Singh | C32: vipul.singh@demo.aivilabs.com | D32: SEC26ME243 | E32: ME | F32: 6.9 | G32: 2026
A33: Bad Row (Duplicate) | B33: Rahul Mishra | C33: rahul.mishra@demo.aivilabs.com | D33: SEC26CSE099 | E33: CSE | F33: 7.1 | G33: 2026 (Duplicate enrollment SEC26CSE099 — expected row error)

Sheet Test Suites — Master
A1: AIVI CAREER & CAMPUS OS — MASTER TEST SUITES TRACKER
A2: Test ID | B2: Suite | C2: Module / Screen | D2: Route / URL | E2: Actor (account) | F2: Preconditions | G2: Test Steps (numbered, one per line) | H2: Expected Result (verbatim strings where known) | I2: If FAIL — Check These First | J2: Severity | K2: Env | L2: Status | M2: Actual Result (what you saw) | N2: Bug ID | O2: Tested By | P2: Date | Q2: Source
A3: S00-T001 | B3: S00 — PRODUCTION SMOKE | C3: Landing / Home | D3: / | E3: Unauthenticated | F3: Browser open | G3: 1. Navigate to https://aivilabs.com/ 2. Observe page header, hero section, and pricing table | H3: Page loads cleanly. Production header renders. No blank screens. | I3: 1. Check internet connection 2. confirm the URL bar shows https://aivilabs.com (production) | J3: P0 | K3: Production | L3: Not Run | Q3: ch01/§4, ch09/§3
A4: S00-T002 | B4: S00 — PRODUCTION SMOKE | C4: Auth Landing | D4: /auth | E4: Unauthenticated | F4: Browser open | G4: 1. Click 'Sign In' button on header or navigate to /auth | H4: Auth card renders with options: Email/Password login, Signup tab, and 'Continue with Google' button. | I4: 1. confirm the URL bar shows https://aivilabs.com (production) 2. Check console for script loading errors | J4: P0 | K4: Production | L4: Not Run | Q4: ch02/Route-2
A5: S00-T003 | B5: S00 — PRODUCTION SMOKE | C5: Staff Login | D5: /campus/login | E5: TPO Admin | F5: TPO account exists | G5: 1. Navigate to /campus/login 2. Enter tpo.director@demo.aivilabs.com and password DemoUser@2026 3. Click 'Sign In' | H5: Authentication succeeds. User lands on /campus showing 'Sunrise Engineering College TPO Command Center'. | I5: 1. confirm the URL bar shows https://aivilabs.com (production) 2. Is email verified? 3. Is password exact (DemoUser@2026)? | J5: P0 | K5: Production | L5: Not Run | Q5: ch03/FLOW-CAMPUS-01, ch11
A6: S00-T004 | B6: S00 — PRODUCTION SMOKE | C6: Campus Dashboard | D6: /campus | E6: TPO Admin | F6: Logged in as TPO Admin | G6: 1. Observe /campus dashboard metrics and AES score band distribution | H6: Dashboard displays student count (242), active drives, and AES score bands (<40, 40-60, 60-75, 75+). | I6: 1. confirm the URL bar shows https://aivilabs.com (production) 2. Check if demo campus is seeded (ch.11) | J6: P1 | K6: Production | L6: Not Run | Q6: ch03/FLOW-CAMPUS-01
A7: S00-T005 | B7: S00 — PRODUCTION SMOKE | C7: Student Login | D7: /auth | E7: Student 1 | F7: Student account exists | G7: 1. Navigate to /login 2. Enter student1@demo.aivilabs.com and password DemoStudent@2026 3. Click 'Sign In' | H7: Authentication succeeds. SPA redirects student to /dashboard. | I7: 1. confirm the URL bar shows https://aivilabs.com (production) 2. Is email verified? 3. Check user claims | J7: P0 | K7: Production | L7: Not Run | Q7: ch03/FLOW-AUTH-02, ch11
A8: S00-T006 | B8: S00 — PRODUCTION SMOKE | C8: Student Dashboard | D8: /dashboard | E8: Student 1 | F8: Logged in as Student 1 | G8: 1. Observe B2C SaaS dashboard home | H8: Dashboard displays recent analysis history cards, usage limits, and quick action cards. | I8: 1. confirm the URL bar shows https://aivilabs.com (production) 2. Verify AuthContext state | J8: P1 | K8: Production | L8: Not Run | Q8: ch02/Route-20
A9: S00-T007 | B9: S00 — PRODUCTION SMOKE | C9: Resume Intelligence | D9: /dashboard/resume | E9: Student 1 | F9: Logged in as Student 1 | G9: 1. Open /dashboard/resume 2. Paste sample resume text (>=50 chars) 3. Click 'Run AI Resume Scoring' | H9: AI analysis completes. Screen displays overall score (0-100), Score Ring, ATS compatibility score, and bullet suggestions. | I9: 1. confirm the URL bar shows https://aivilabs.com (production) 2. Check remaining Free plan uses 3. Check AI rate limit (3/min) | J9: P0 | K9: Production | L9: Not Run | Q9: ch03/FLOW-B2C-01
A10: S00-T008 | B10: S00 — PRODUCTION SMOKE | C10: Public Contact | D10: /contact | E10: Unauthenticated | F10: Browser open | G10: 1. Navigate to /contact 2. Observe contact form rendering | H10: Contact page renders with name, email, subject, message fields, and 'Send Message' CTA. | I10: 1. confirm the URL bar shows https://aivilabs.com (production) | J10: P2 | K10: Production | L10: Not Run | Q10: ch02/Route-10
A11: S00-T009 | B11: S00 — PRODUCTION SMOKE | C11: 404 Error Page | D11: /non-existent-page-xyz | E11: Unauthenticated | F11: Browser open | G11: 1. Navigate to https://aivilabs.com/non-existent-page-xyz | H11: Screen renders branded 404 view: 'Page Not Found', explaining page does not exist, with button 'Return to Home'. | I11: 1. confirm the URL bar shows https://aivilabs.com (production) 2. Check App.tsx wildcard route | J11: P2 | K11: Production | L11: Not Run | Q11: ch02/§2.1
A12: S00-T010 | B12: S00 — PRODUCTION SMOKE | C12: Mobile Viewport | D12: / | E12: Unauthenticated | F12: Chrome DevTools open (375px) | G12: 1. Open DevTools (F12) -> Toggle Device Toolbar -> Select iPhone SE (375px width) 2. Load / | H12: Responsive layout renders without horizontal overflow or overlapping text. Mobile hamburger menu works. | I12: 1. confirm the URL bar shows https://aivilabs.com (production) | J12: P2 | K12: Production | L12: Not Run | Q12: ch01/§5
A13: S01-T001 | B13: S01 — AUTH & ONBOARDING | C13: Email Registration | D13: /auth | E13: Public Visitor | F13: Throwaway email ready | G13: 1. Open /auth -> Click 'Sign Up' tab 2. Enter Name 'Test User', email 'qa.throwaway99@demo.aivilabs.com', password 'Password@123' 3. Click 'Create Account' | H13: Account created. SPA redirects to /verify-email showing message: 'Verification email sent to qa.throwaway99@demo.aivilabs.com.' | I13: 1. confirm the URL bar shows https://aivilabs.com (production) 2. Did user already exist? | J13: P0 | K13: Production | L13: Not Run | Q13: ch03/FLOW-AUTH-01
A14: S01-T002 | B14: S01 — AUTH & ONBOARDING | C14: Duplicate Email Signup | D14: /auth | E14: Public Visitor | F14: Existing user email | G14: 1. Open /auth -> Sign Up tab 2. Enter existing email 'student1@demo.aivilabs.com' and password 'Password@123' 3. Click 'Create Account' | H14: Form displays verbatim alert message: 'An account with this email already exists.' | I14: 1. confirm the URL bar shows https://aivilabs.com (production) 2. Check ERR-001 mapping in ch.08 | J14: P1 | K14: Production | L14: Not Run | Q14: ch08/ERR-001
... A158: S11-T008 | B158: S11 — CROSS-CUTTING & REGRESSION SPOT CHECKS | C158: Browser Refresh State Integrity | D158: /dashboard/resume | E158: Student 1 | F158: Analysis displayed | G158: 1. Complete resume scoring analysis 2. Press F5 (Browser Refresh) | H158: App refreshes cleanly, maintains user session, and re-renders recent analysis from Firestore. | I158: 1. confirm the URL bar shows https://aivilabs.com (production) 2. Check React Query caching & AuthContext init | J158: P2 | K158: Production | L158: Not Run | Q158: ch01/§1

Sheet Error Diagnosis Guide
A1: AIVI CAREER & CAMPUS OS — MASTER ERROR CATALOGUE & QA DIAGNOSIS GUIDE
A3: 1. Master Error & Message Catalogue (From Chapter 08)
A4: Error ID | B4: Exact Message Text (Verbatim) | C4: Screen / Component File | D4: Precise Trigger Condition | E4: Recommended User Action | F4: Retryable
A5: ERR-001 | B5: An account with this email already exists. | C5: Auth.tsx | D5: Signup with email already registered in Firebase Auth | E5: Click 'Sign In' instead or reset password | F5: No
A6: ERR-002 | B6: Password should be at least 6 characters. | C6: Auth.tsx | D6: Signup password string length < 6 | E6: Enter a stronger password (>=6 characters) | F6: Yes
A7: ERR-003 | B7: Invalid email or password. | C7: Auth.tsx | D7: Auth sign-in failure (auth/invalid-credential) | E7: Verify email and password credentials | F7: Yes
A8: ERR-004 | B8: Email verification required. | C8: ProtectedRoute.tsx | D8: Authenticated user has emailVerified == false | E8: Check inbox for verification link or click Resend | F8: Yes
A9: ERR-005 | B9: Google sign-in popup was closed. | C9: Auth.tsx | D9: User closes Google OAuth popup window before completion | E9: Re-click 'Continue with Google' | F9: Yes
A10: ERR-006 | B10: Popup blocked by browser. Enable popups to sign in with Google. | C10: Auth.tsx | D10: Browser popup blocker prevents OAuth window | E10: Allow popups for domain in browser settings | F10: Yes
A11: ERR-007 | B11: If an account exists for this email, a reset link has been sent. | C11: Auth.tsx | D11: User submits password reset form | E11: Check email inbox for password reset link | F11: Yes
A12: ERR-008 | B12: Free tier limit reached. Upgrade to Starter or Pro for unlimited resume scoring. | C12: ResumeIntelligence.tsx | D12: Free user exceeds 2 lifetime resume analyses | E12: Upgrade plan via Upgrade Modal | F12: No
A13: ERR-009 | B13: Resume text is too short to analyze. | C13: ResumeUploadForm.tsx | D13: Uploaded/pasted resume text length < 50 characters | E13: Provide a complete resume document | F13: Yes
A14: ERR-010 | B14: AI service is temporarily unavailable. Please try again. | C14: analysisService.ts | D14: Gemini API timeout or backend error | E14: Wait 10 seconds and re-click Analyze | F14: Yes
A15: ERR-011 | B15: Please provide both a resume and a job description. | C15: JobFitAnalysis.tsx | D15: Job fit form submitted with missing resume or JD | E15: Fill in both text fields before analyzing | F15: Yes
... A24: ERR-020 | B24: Microphone access denied. Please enable mic permissions in browser settings to use voice mode. | C24: CampusInterviews.tsx | D24: User rejects browser microphone prompt | E24: Grant microphone permission in browser bar | F24: Yes
A27: 2. QA Diagnostic Scenarios (Symptom -> Cause -> Checks)
A28: # | B28: Observed User Symptom | C28: Probable Root Cause | D28: First Diagnostic Checks for QA Tester
A29: 1 | B29: Login succeeds, but immediately redirects back to /verify-email | C29: User's email is not verified in Firebase Auth | D29: Check user.emailVerified in Firebase Console. Click 'Resend Email' and click link.
A30: 2 | B30: Upgrade to Starter modal opens when clicking LinkedIn Optimizer | C30: User is on Free plan (linkedin_optimize requires paid tier) | D30: Check user_plans/{uid} document. Verify planType is 'starter' or 'pro'.
A31: 3 | B31: AI Analysis fails with 'Rate limit exceeded' toast | C31: User clicked Analyze >3 times in under 1 minute | D31: Inspect Firestore collection ai_rate_limits/{uid}_careerAnalysis. Wait 60s for reset.
A32: 4 | B32: Razorpay payment modal fails to launch after clicking Upgrade | C32: Script blocked by browser adblocker or strict CSP policy | D32: Open browser Developer Console. Check for blocked request to checkout.razorpay.com.
A33: 5 | B33: Campus student cannot launch Vernacular Mock Interview | C33: Student has not accepted DPDP Privacy Consent prompt | D33: Check profiles/{uid} doc for dpdpConsent: true. Accept consent modal on screen.
A34: 6 | B34: Coordinator cannot view CSE student profiles | C34: Coordinator lacks 'CSE' in custom claim branchScope | D34: Inspect JWT ID token claims or tenant_members doc. Verify branchScope array.
A35: 7 | B35: CSV Student Import fails with 'Tenant seat limit reached' | C35: CSV row count + seatsUsed exceeds tenant seats quota | D35: Inspect tenants/{tenantId} document. Compare seatsUsed vs seats.
A36: 8 | B36: Platform Admin Console displays 'Access Denied' | C36: Account email is not listed in PLATFORM_ADMIN_ALLOWLIST | D36: Verify email in functions/src/demoSeeder.ts. Run bootstrapPlatformAdmin endpoint.
A37: 9 | B37: Vernacular Voice Interview fails to transcribe speech | C37: Microphone blocked or Bhashini voice provider timeout | D37: Check browser mic permissions. Verify network request to bhashini.gov.in.
A38: 10 | B38: 1-Click Demo Campus seeder fails with 'Confirmation Required' | C38: Tenant demo-sunrise already exists in Firestore | D38: Inspect tenants/{tenantId}. Seeder execution is FOUNDER-ONLY on Production.
A40: 3. Protocol: If Nothing Here Matches Your Problem
A41: 1. Perform a hard browser refresh (Ctrl + Shift + R or Cmd + Shift + R) to clear cached JavaScript bundles.
A42: 2. confirm the URL bar shows https://aivilabs.com (production).
A43: 3. Test the exact same flow in an Incognito / Private window to rule out browser extension interference.
A44: 4. Try logging in with a different test account of the same role from the Test Accounts sheet.
A45: 5. Open Developer Console (F12) -> Console & Network tabs -> Capture screenshot of any red error stack trace.
A46: 6. File a bug on 'Bug Log' sheet using the mandatory 5-line format, attach screenshot link, and write 'checks done: hard refresh, incognito, console inspect'.

Sheet Bug Log
A1: AIVI CAREER & CAMPUS OS — FORMAL QA BUG LOG
A2: Bug ID | B2: Date | C2: Found via Test ID | D2: Module / Screen | E2: Severity | F2: Found By | G2: ① What I did | H2: ② What I expected | I2: ③ What happened (exact message) | J2: ④ URL + Env + Account | K2: ⑤ Screenshot/recording link | L2: Checks done before filing | M2: Status | N2: Dev Notes (founder/builder) | O2: Retested By + Date
A3: BUG-001 | B3: 2026-07-23 | C3: S01-T005 | D3: Auth / Login | E3: P2 | F3: Intern Lead | G3: 1. Navigated to https://aivilabs.com/login 2. Entered email 'test.unverified@demo.aivilabs.com' and password 'DemoUser@2026' 3. Clicked 'Sign In' | H3: User should log in and land on /dashboard | I3: Screen redirected to /verify-email showing banner 'Email verification required.' | J3: https://aivilabs.com/login | Production | test.unverified@demo.aivilabs.com | K3: https://drive.google.com/file/d/sample-bug-001/view | L3: checks done: checked user in console, emailVerified is false, password is correct, email reset link arrives. Working as designed per ch.05. | M3: Not a Bug | N3: Expected behavior per Auth security rules (ch.05). Unverified accounts are strictly gated to /verify-email. | O3: Founder / 2026-07-23
A4: BUG-002
A5: BUG-003
A6: BUG-004
A7: BUG-005
A8: BUG-006
A9: BUG-007
A10: BUG-008
A11: BUG-009
A12: BUG-010
A13: BUG-011
A14: BUG-012
A15: BUG-013
... A63: BUG-061

Sheet Daily Report & Progress
A1: AIVI CAREER & CAMPUS OS — TESTING PROGRESS DASHBOARD & DAILY LOG
A3: 1. Intern Daily Testing Execution Log
A4: Date | B4: Intern Name | C4: Suite(s) Worked | D4: TCs Executed | E4: Passed | F4: Failed | G4: Blocked | H4: Bugs Filed (IDs) | I4: Blockers / Daily Notes
A22: 2. Automated Test Execution Progress Dashboard (Computed via Live Formulas)
A23: Suite Name | B23: Suite Description | C23: Total TCs | D23: Passed | E23: Failed | F23: Blocked | G23: Not Run | H23: % Complete | I23: Gate Readiness Status
A24: S00 | B24: Daily Production Environment Smoke Suite | C24: =COUNTIF('Test Suites — Master'!$B$3:$B$200, "S00 — PRODUCTION SMOKE") | D24: =COUNTIFS('Test Suites — Master'!$B$3:$B$200, "S00 — PRODUCTION SMOKE", 'Test Suites — Master'!$L$3:$L$200, "Pass") | E24: =COUNTIFS('Test Suites — Master'!$B$3:$B$200, "S00 — PRODUCTION SMOKE", 'Test Suites — Master'!$L$3:$L$200, "Fail") | F24: =COUNTIFS('Test Suites — Master'!$B$3:$B$200, "S00 — PRODUCTION SMOKE", 'Test Suites — Master'!$L$3:$L$200, "Blocked") | G24: =COUNTIFS('Test Suites — Master'!$B$3:$B$200, "S00 — PRODUCTION SMOKE", 'Test Suites — Master'!$L$3:$L$200, "Not Run") | H24: =IF(C24>0, (D24+E24+F24)/C24, 0) | I24: =IF(D24=C24, "READY", IF(E24>0, "FAILURES PRESENT", "IN PROGRESS"))
A25: S01 | B25: Authentication, Signup, Verification, SSO & Reset | C25: =COUNTIF('Test Suites — Master'!$B$3:$B$200, "S01 — AUTH & ONBOARDING") | D25: =COUNTIFS('Test Suites — Master'!$B$3:$B$200, "S01 — AUTH & ONBOARDING", 'Test Suites — Master'!$L$3:$L$200, "Pass") | E25: =COUNTIFS('Test Suites — Master'!$B$3:$B$200, "S01 — AUTH & ONBOARDING", 'Test Suites — Master'!$L$3:$L$200, "Fail") | F25: =COUNTIFS('Test Suites — Master'!$B$3:$B$200, "S01 — AUTH & ONBOARDING", 'Test Suites — Master'!$L$3:$L$200, "Blocked") | G25: =COUNTIFS('Test Suites — Master'!$B$3:$B$200, "S01 — AUTH & ONBOARDING", 'Test Suites — Master'!$L$3:$L$200, "Not Run") | H25: =IF(C25>0, (D25+E25+F25)/C25, 0) | I25: =IF(D25=C25, "READY", IF(E25>0, "FAILURES PRESENT", "IN PROGRESS"))
A26: S02 | B26: 8 B2C SaaS AI Career Analysis Tools & Limits | C26: =COUNTIF('Test Suites — Master'!$B$3:$B$200, "S02 — B2C MODULES") | D26: =COUNTIFS('Test Suites — Master'!$B$3:$B$200, "S02 — B2C MODULES", 'Test Suites — Master'!$L$3:$L$200, "Pass") | E26: =COUNTIFS('Test Suites — Master'!$B$3:$B$200, "S02 — B2C MODULES", 'Test Suites — Master'!$L$3:$L$200, "Fail") | F26: =COUNTIFS('Test Suites — Master'!$B$3:$B$200, "S02 — B2C MODULES", 'Test Suites — Master'!$L$3:$L$200, "Blocked") | G26: =COUNTIFS('Test Suites — Master'!$B$3:$B$200, "S02 — B2C MODULES", 'Test Suites — Master'!$L$3:$L$200, "Not Run") | H26: =IF(C26>0, (D26+E26+F26)/C26, 0) | I26: =IF(D26=C26, "READY", IF(E26>0, "FAILURES PRESENT", "IN PROGRESS"))
A27: S03 | B27: Razorpay Order Creation, Checkout & Plan Updates (Founder Live Only) | C27: =COUNTIF('Test Suites — Master'!$B$3:$B$200, "S03 — PAYMENTS LIVE-MODE") | D27: =COUNTIFS('Test Suites — Master'!$B$3:$B$200, "S03 — PAYMENTS LIVE-MODE", 'Test Suites — Master'!$L$3:$L$200, "Pass") | E27: =COUNTIFS('Test Suites — Master'!$B$3:$B$200, "S03 — PAYMENTS LIVE-MODE", 'Test Suites — Master'!$L$3:$L$200, "Fail") | F27: =COUNTIFS('Test Suites — Master'!$B$3:$B$200, "S03 — PAYMENTS LIVE-MODE", 'Test Suites — Master'!$L$3:$L$200, "Blocked") | G27: =COUNTIFS('Test Suites — Master'!$B$3:$B$200, "S03 — PAYMENTS LIVE-MODE", 'Test Suites — Master'!$L$3:$L$200, "Not Run") | H27: =IF(C27>0, (D27+E27+F27)/C27, 0) | I27: =IF(D27=C27, "READY", IF(E27>0, "FAILURES PRESENT", "IN PROGRESS"))
A28: S04 | B28: Platform Admin Console, Provisioning & Seeder | C28: =COUNTIF('Test Suites — Master'!$B$3:$B$200, "S04 — CAMPUS PLATFORM ADMIN") | D28: =COUNTIFS('Test Suites — Master'!$B$3:$B$200, "S04 — CAMPUS PLATFORM ADMIN", 'Test Suites — Master'!$L$3:$L$200, "Pass") | E28: =COUNTIFS('Test Suites — Master'!$B$3:$B$200, "S04 — CAMPUS PLATFORM ADMIN", 'Test Suites — Master'!$L$3:$L$200, "Fail") | F28: =COUNTIFS('Test Suites — Master'!$B$3:$B$200, "S04 — CAMPUS PLATFORM ADMIN", 'Test Suites — Master'!$L$3:$L$200, "Blocked") | G28: =COUNTIFS('Test Suites — Master'!$B$3:$B$200, "S04 — CAMPUS PLATFORM ADMIN", 'Test Suites — Master'!$L$3:$L$200, "Not Run") | H28: =IF(C28>0, (D28+E28+F28)/C28, 0) | I28: =IF(D28=C28, "READY", IF(E28>0, "FAILURES PRESENT", "IN PROGRESS"))
A29: S05 | B29: Campus TPO Dashboard, Drives, CSV Import & Vault | C29: =COUNTIF('Test Suites — Master'!$B$3:$B$200, "S05 — CAMPUS TPO & STAFF") | D29: =COUNTIFS('Test Suites — Master'!$B$3:$B$200, "S05 — CAMPUS TPO & STAFF", 'Test Suites — Master'!$L$3:$L$200, "Pass") | E29: =COUNTIFS('Test Suites — Master'!$B$3:$B$200, "S05 — CAMPUS TPO & STAFF", 'Test Suites — Master'!$L$3:$L$200, "Fail") | F29: =COUNTIFS('Test Suites — Master'!$B$3:$B$200, "S05 — CAMPUS TPO & STAFF", 'Test Suites — Master'!$L$3:$L$200, "Blocked") | G29: =COUNTIFS('Test Suites — Master'!$B$3:$B$200, "S05 — CAMPUS TPO & STAFF", 'Test Suites — Master'!$L$3:$L$200, "Not Run") | H29: =IF(C29>0, (D29+E29+F29)/C29, 0) | I29: =IF(D29=C29, "READY", IF(E29>0, "FAILURES PRESENT", "IN PROGRESS"))
A30: S06 | B30: Coordinator Branch-Scoped Access Control | C30: =COUNTIF('Test Suites — Master'!$B$3:$B$200, "S06 — COORDINATOR BRANCH SCOPE") | D30: =COUNTIFS('Test Suites — Master'!$B$3:$B$200, "S06 — COORDINATOR BRANCH SCOPE", 'Test Suites — Master'!$L$3:$L$200, "Pass") | E30: =COUNTIFS('Test Suites — Master'!$B$3:$B$200, "S06 — COORDINATOR BRANCH SCOPE", 'Test Suites — Master'!$L$3:$L$200, "Fail") | F30: =COUNTIFS('Test Suites — Master'!$B$3:$B$200, "S06 — COORDINATOR BRANCH SCOPE", 'Test Suites — Master'!$L$3:$L$200, "Blocked") | G30: =COUNTIFS('Test Suites — Master'!$B$3:$B$200, "S06 — COORDINATOR BRANCH SCOPE", 'Test Suites — Master'!$L$3:$L$200, "Not Run") | H30: =IF(C30>0, (D30+E30+F30)/C30, 0) | I30: =IF(D30=C30, "READY", IF(E30>0, "FAILURES PRESENT", "IN PROGRESS"))
A31: S07 | B31: Campus Student Portal, DPDP & Vernacular Voice | C31: =COUNTIF('Test Suites — Master'!$B$3:$B$200, "S07 — CAMPUS STUDENT") | D31: =COUNTIFS('Test Suites — Master'!$B$3:$B$200, "S07 — CAMPUS STUDENT", 'Test Suites — Master'!$L$3:$L$200, "Pass") | E31: =COUNTIFS('Test Suites — Master'!$B$3:$B$200, "S07 — CAMPUS STUDENT", 'Test Suites — Master'!$L$3:$L$200, "Fail") | F31: =COUNTIFS('Test Suites — Master'!$B$3:$B$200, "S07 — CAMPUS STUDENT", 'Test Suites — Master'!$L$3:$L$200, "Blocked") | G31: =COUNTIFS('Test Suites — Master'!$B$3:$B$200, "S07 — CAMPUS STUDENT", 'Test Suites — Master'!$L$3:$L$200, "Not Run") | H31: =IF(C31>0, (D31+E31+F31)/C31, 0) | I31: =IF(D31=C31, "READY", IF(E31>0, "FAILURES PRESENT", "IN PROGRESS"))
A32: S08 | B32: Public Marketing Pages, SEO Landing & Contact | C32: =COUNTIF('Test Suites — Master'!$B$3:$B$200, "S08 — PUBLIC & MARKETING") | D32: =COUNTIFS('Test Suites — Master'!$B$3:$B$200, "S08 — PUBLIC & MARKETING", 'Test Suites — Master'!$L$3:$L$200, "Pass") | E32: =COUNTIFS('Test Suites — Master'!$B$3:$B$200, "S08 — PUBLIC & MARKETING", 'Test Suites — Master'!$L$3:$L$200, "Fail") | F32: =COUNTIFS('Test Suites — Master'!$B$3:$B$200, "S08 — PUBLIC & MARKETING", 'Test Suites — Master'!$L$3:$L$200, "Blocked") | G32: =COUNTIFS('Test Suites — Master'!$B$3:$B$200, "S08 — PUBLIC & MARKETING", 'Test Suites — Master'!$L$3:$L$200, "Not Run") | H32: =IF(C32>0, (D32+E32+F32)/C32, 0) | I32: =IF(D32=C32, "READY", IF(E32>0, "FAILURES PRESENT", "IN PROGRESS"))
A33: S09 | B33: Route Guards, Storage Rules & Header Security | C33: =COUNTIF('Test Suites — Master'!$B$3:$B$200, "S09 — SECURITY GUARDS & PERMISSIONS") | D33: =COUNTIFS('Test Suites — Master'!$B$3:$B$200, "S09 — SECURITY GUARDS & PERMISSIONS", 'Test Suites — Master'!$L$3:$L$200, "Pass") | E33: =COUNTIFS('Test Suites — Master'!$B$3:$B$200, "S09 — SECURITY GUARDS & PERMISSIONS", 'Test Suites — Master'!$L$3:$L$200, "Fail") | F33: =COUNTIFS('Test Suites — Master'!$B$3:$B$200, "S09 — SECURITY GUARDS & PERMISSIONS", 'Test Suites — Master'!$L$3:$L$200, "Blocked") | G33: =COUNTIFS('Test Suites — Master'!$B$3:$B$200, "S09 — SECURITY GUARDS & PERMISSIONS", 'Test Suites — Master'!$L$3:$L$200, "Not Run") | H33: =IF(C33>0, (D33+E33+F33)/C33, 0) | I33: =IF(D33=C33, "READY", IF(E33>0, "FAILURES PRESENT", "IN PROGRESS"))
A34: S10 | B34: Production Environment Read-Only Smoke Suite | C34: =COUNTIF('Test Suites — Master'!$B$3:$B$200, "S10 — PRODUCTION READ-ONLY SMOKE") | D34: =COUNTIFS('Test Suites — Master'!$B$3:$B$200, "S10 — PRODUCTION READ-ONLY SMOKE", 'Test Suites — Master'!$L$3:$L$200, "Pass") | E34: =COUNTIFS('Test Suites — Master'!$B$3:$B$200, "S10 — PRODUCTION READ-ONLY SMOKE", 'Test Suites — Master'!$L$3:$L$200, "Fail") | F34: =COUNTIFS('Test Suites — Master'!$B$3:$B$200, "S10 — PRODUCTION READ-ONLY SMOKE", 'Test Suites — Master'!$L$3:$L$200, "Blocked") | G34: =COUNTIFS('Test Suites — Master'!$B$3:$B$200, "S10 — PRODUCTION READ-ONLY SMOKE", 'Test Suites — Master'!$L$3:$L$200, "Not Run") | H34: =IF(C34>0, (D34+E34+F34)/C34, 0) | I34: =IF(D34=C34, "READY", IF(E34>0, "FAILURES PRESENT", "IN PROGRESS"))
A35: S11 | B35: Responsiveness, Contrast & Regression Spot-Checks | C35: =COUNTIF('Test Suites — Master'!$B$3:$B$200, "S11 — CROSS-CUTTING & REGRESSION SPOT CHECKS") | D35: =COUNTIFS('Test Suites — Master'!$B$3:$B$200, "S11 — CROSS-CUTTING & REGRESSION SPOT CHECKS", 'Test Suites — Master'!$L$3:$L$200, "Pass") | E35: =COUNTIFS('Test Suites — Master'!$B$3:$B$200, "S11 — CROSS-CUTTING & REGRESSION SPOT CHECKS", 'Test Suites — Master'!$L$3:$L$200, "Fail") | F35: =COUNTIFS('Test Suites — Master'!$B$3:$B$200, "S11 — CROSS-CUTTING & REGRESSION SPOT CHECKS", 'Test Suites — Master'!$L$3:$L$200, "Blocked") | G35: =COUNTIFS('Test Suites — Master'!$B$3:$B$200, "S11 — CROSS-CUTTING & REGRESSION SPOT CHECKS", 'Test Suites — Master'!$L$3:$L$200, "Not Run") | H35: =IF(C35>0, (D35+E35+F35)/C35, 0) | I35: =IF(D35=C35, "READY", IF(E35>0, "FAILURES PRESENT", "IN PROGRESS"))
A36: OVERALL TOTALS | B36: All 12 Test Suites Combined | C36: =SUM(C24:C35) | D36: =SUM(D24:D35) | E36: =SUM(E24:E35) | F36: =SUM(F24:F35) | G36: =SUM(G24:G35) | H36: =IF(C36>0, (D36+E36+F36)/C36, 0) | I36: =IF(D36=C36, "RELEASE READY", "TESTING IN PROGRESS")
A39: GATE 1 READY = S00–S03 100% executed, 0 open P0/P1 · GATE 2 = S04–S09 100% executed, 0 open P0 · GATE 3 = S10 read-only verified by founder
